webclip/__init__.py
webclip/cli.py
webclip/webclip.py
webclip-0.0.2.dist-info/AUTHORS.rst
webclip-0.0.2.dist-info/LICENSE
webclip-0.0.2.dist-info/METADATA
webclip-0.0.2.dist-info/WHEEL
webclip-0.0.2.dist-info/entry_points.txt
webclip-0.0.2.dist-info/top_level.txt
webclip-0.0.2.dist-info/RECORD
