Metadata-Version: 2.1
Name: webclip
Version: 0.0.2
Summary: Web Clipper for all your needs!
Home-page: https://github.com/AgarwalPragy/py-webclip
Author: Pragy Agarwal
Author-email: agar.pragy@gmail.com
License: GNU General Public License v3
Keywords: webclip
Platform: UNKNOWN
Classifier: Development Status :: 2 - Pre-Alpha
Classifier: Intended Audience :: Developers
Classifier: License :: OSI Approved :: GNU General Public License v3 (GPLv3)
Classifier: Natural Language :: English
Classifier: Programming Language :: Python :: 3
Classifier: Programming Language :: Python :: 3.5
Classifier: Programming Language :: Python :: 3.6
Classifier: Programming Language :: Python :: 3.7
Classifier: Programming Language :: Python :: 3.8
Requires-Python: >=3.5
Requires-Dist: Click (>=7.0)
